Workbook

Sheet E.General
B2: Modelo Generico Presupuesto para la ejecución del Proyecto de Investigación
B4: Ítem | C4: Valor en Pesos Colombianos ( $) | D4: Fuente de Financiamiento* | G4: Total ($)
D5: Fuente A | E5: Fuente B | F5: Recursos propios
B6: A. Personal
B7: Docente Investigador | C7: =+'A-Personal'!F7 -> 4000000 | D7: =+C7*40% -> 1600000 | E7: =+C7*40% -> 1600000 | F7: =+C7*20% -> 800000 | G7: =+D7+E7+F7 -> 4000000
B8: Docente Investigador | C8: =+'A-Personal'!F8 -> 4000000 | D8: =+C8*40% -> 1600000 | E8: =+C8*40% -> 1600000 | F8: =+C8*20% -> 800000 | G8: =+D8+E8+F8 -> 4000000
B9: Asistente | C9: =+'A-Personal'!F9 -> 0 | D9: =+C9*40% -> 0 | E9: =+C9*40% -> 0 | F9: =+C9*20% -> 0 | G9: =+D9+E9+F9 -> 0
B10: Apoyo Administrativo | C10: =+'A-Personal'!F10 -> 0 | D10: =+C10*40% -> 0 | E10: =+C10*40% -> 0 | F10: =+C10*20% -> 0 | G10: =+D10+E10+F10 -> 0
B11: =+'A-Personal'!B11 -> Subtotal
B12: Subtotal | C12: =+'A-Personal'!F11 -> 8000000 | D12: =SUM(D7:D10) -> 3200000 | E12: =SUM(E7:E10) -> 3200000 | F12: =SUM(F7:F10) -> 1600000 | G12: =SUM(G7:G10) -> 8000000
B13: B. Equipos y Software
B14: =+'B-Equipos'!B6 -> Computador para desarrollo | C14: =+'B-Equipos'!F6 -> 0 | D14: 0 | E14: =+C14*0/100 -> 0 | F14: 0 | G14: =+F14+E14+D14 -> 0
B15: =+'B-Equipos'!B7 -> Software de desarrollo utilizado | C15: =+'B-Equipos'!F7 -> 0 | E15: 0 | G15: =+F15+E15+D15 -> 0
B16: =+'B-Equipos'!B8 -> Servicio de internet | C16: =+'B-Equipos'!F8 -> 400000 | E16: 0 | F16: 400000 | G16: =+F16+E16+D16 -> 400000
B17: Subtotal | C17: =+'B-Equipos'!F10 -> 400000 | D17: =SUM(D14:D16) -> 0 | E17: =SUM(E14:E16) -> 0 | F17: =SUM(F14:F16) -> 400000 | G17: =SUM(G14:G16) -> 400000
B18: C. Viajes y Salidas de Campo
B19: Gasolina | C19: =+'C-Viajes'!F6 -> 0 | D19: =+C19*0 -> 0 | E19: =+C19*0/100 -> 0 | F19: =+C19*1 -> 0 | G19: =+D19+E19+F19 -> 0
B20: Peajes | C20: =+'C-Viajes'!F7 -> 0 | F20: 0 | G20: =+D20+E20+F20 -> 0
B21: Subtotal | C21: =+'C-Viajes'!F9 -> 0 | D21: =SUM(D19:D20) -> 0 | E21: =SUM(E19:E20) -> 0 | F21: =SUM(F19:F20) -> 0 | G21: =SUM(G19:G20) -> 0
B22: D. Materiales
B23: Publicacion / Impresión de documentacion | C23: =+'D-Materiales'!F7 -> 50000 | D23: =+C23*0/100 -> 0 | E23: 0 | F23: =+C23 -> 50000 | G23: =+D23+E23+F23 -> 50000
B24: Papeleria | C24: =+'D-Materiales'!F8 -> 40000 | D24: 0 | E24: 0 | F24: 40000 | G24: =+D24+E24+F24 -> 40000
B25: USB / Almacenamiento | C25: 30000 | D25: 0 | E25: 0 | F25: =+C25 -> 30000 | G25: =+D25+E25+F25 -> 30000
B26: Subtotal | C26: =+'D-Materiales'!F11 -> 120000 | D26: =SUM(D23:D25) -> 0 | E26: =SUM(E23:E25) -> 0 | F26: =SUM(F23:F25) -> 120000 | G26: =SUM(G23:G25) -> 120000
B27: E. Asesorías técnicas y de soporte
B28: Asesoría especializada | C28: =+'E-Ase Tecn. y Soporte'!F7 -> 0 | D28: =+C28*0.3 -> 0 | E28: =+C28*0.7 -> 0 | F28: =+C28*0/100 -> 0 | G28: =+D28+E28+F28 -> 0
B29: Suscripción Revista | C29: =+'E-Ase Tecn. y Soporte'!F8 -> 0 | D29: 0 | E29: 0 | F29: 0 | G29: =+D29+E29+F29 -> 0
B30: Subtotal | C30: =+'E-Ase Tecn. y Soporte'!F10 -> 0 | D30: =SUM(D28:D29) -> 0 | E30: =SUM(E28:E29) -> 0 | F30: =SUM(F28:F29) -> 0 | G30: =SUM(G28:G29) -> 0
B31: E. Otros
B32: Consumo de energia | C32: =+'F-Otros'!F7 -> 200000 | D32: =+C32*0/100 -> 0 | E32: =+C32*0/100 -> 0 | F32: =+C32*1 -> 200000 | G32: =+D32+E32+F32 -> 200000
B33: Almacenamiento / USB para respaldo | C33: =+'F-Otros'!F8 -> 30000 | F33: =+C33*1 -> 30000 | G33: =+D33+E33+F33 -> 30000
B34: Seguros | C34: =+'F-Otros'!F9 -> 0 | F34: =+C34*1 -> 0 | G34: =+D34+E34+F34 -> 0
B35: Tasas de inmpuestos | C35: =+'F-Otros'!F10 -> 0 | F35: =+C35*1 -> 0 | G35: =+D35+E35+F35 -> 0
B36: Alimentacion | C36: =+'F-Otros'!F11 -> 0 | F36: =+C36*1 -> 0 | G36: =+D36+E36+F36 -> 0
B37: Subtotal | C37: =+'F-Otros'!F12 -> 230000 | D37: =SUM(D32:D36) -> 0 | E37: =SUM(E32:E36) -> 0 | F37: =SUM(F32:F36) -> 230000 | G37: =SUM(G32:G36) -> 230000
B38: Total | C38: =+C12+C17+C21+C26+C30+C37 -> 8750000 | D38: =+D12+D17+D21+D26+D30+D37 -> 3200000 | E38: =+E12+E17+E21+E26+E30+E37 -> 3200000 | F38: =+F12+F17+F21+F26+F30+F37 -> 2350000 | G38: =+G12+G17+G21+G26+G30+G37 -> 8750000
B39: Porcentaje | C39: 1 | D39: =+D38/$C$38 -> 0.36571429 | E39: =+E38/$C$38 -> 0.36571429 | F39: =+F38/$C$38 -> 0.26857143 | G39: =+F39+E39+D39 -> 1
B40: *Rubros No Financiables con fuentes externas

Sheet A-Personal
B3: Personal requerido para la ejecución del proyecto.
B5: Categoría | C5: Salario - Honorario - Mensual ($) | D5: Cantidad | E5: Tiempo de Vinculación en meses | F5: Importe $
B7: Estudiante Desarrolador 1 | C7: 1000000 | D7: 1 | E7: 4 | F7: =+C7*D7*E7 -> 4000000
B8: Estudiante Desarrolador 2 | C8: 1000000 | D8: 1 | E8: 4 | F8: =+C8*D8*E8 -> 4000000
B9: Docente / Gestor de Conocimiento | C9: 0 | D9: 1 | E9: 4 | F9: =+E9*D9*C9 -> 0
F10: =+E10*D10*C10 -> 0
B11: Subtotal | F11: =SUM(F7:F10) -> 8000000

Sheet B-Equipos
B2: Equipos y software
B4: Descripción | C4: Unidad de Medida | D4: Cantidad | E4: Precio Unitario ($) | F4: Importe $
B6: Computador para desarrollo | C6: Unidad | D6: 2 | E6: 0 | F6: 0
B7: Software de desarrollo utilizado | C7: Paquete | D7: 1 | E7: 0 | F7: 0
B8: Servicio de internet | C8: Mes | D8: 4 | E8: 100000 | F8: 400000
F9: =+D9*E9 -> 0
B10: Subtotal | F10: =SUM(F6:F9) -> 400000

Sheet C-Viajes
B3: Viajes y salidas de Campo
B5: Concepto | C5: Tarifa diaria en $ | D5: Numero de días por viaje/salida de campo | E5: Número de Viajes y/o salidas de campo | F5: Importe ($)
B6: Gasolina | C6: 0 | D6: 0 | E6: 0 | F6: 0
B7: Peajes | C7: 0 | D7: 0 | E7: 0 | F7: 0
F8: =+E8*D8*C8 -> 0
B9: Subtotal | F9: =SUM(F6:F8) -> 0

Sheet D-Materiales
B3: Materiales
B5: Descripción del Material | C5: Unidad de medida | D5: Cantidad | E5: Precio Unitario ($) | F5: Importe $
B7: Impresiones y Papeleria | C7: Unidad | D7: 1 | E7: 50000 | F7: =+E7*D7 -> 50000
B8: Impresión de Poster Academico | C8: Unidad | D8: 1 | E8: 40000 | F8: =+E8*D8 -> 40000
B9: Material para la presentacion | C9: Unidad | D9: 1 | E9: 30000 | F9: =+E9*D9 -> 30000
B11: Subtotal | F11: =SUM(F7:F10) -> 120000

Sheet E-Ase Tecn. y Soporte
B3: Asesorías técnicas y soporte
B5: Descripción | C5: Unidad de medida | D5: Cantidad | E5: Precio Unitario ($) | F5: Importe $
B7: Asesoría especializada | C7: H | D7: 0 | E7: 0 | F7: 0
B8: Suscripción Revista | C8: Unidad | D8: 0 | E8: 0 | F8: 0
F9: =+E9*D9 -> 0
B10: Subtotal | F10: =SUM(F7:F9) -> 0

Sheet F-Otros
B3: Otros
B5: Descripción | C5: Unidad de medida | D5: Cantidad | E5: Precio Unitario ($) | F5: Importe $
B7: Consumo de energia Electrica | C7: Mes | D7: 4 | E7: 50000 | F7: =+E7*D7 -> 200000
B8: Almacenamiento/ USB para respaldo | C8: Unidad | D8: 1 | E8: 30000 | F8: =+E8*D8 -> 30000
B9: Garantias | D9: 0 | E9: 0 | F9: =+E9*D9 -> 0
B10: Tasas Impuestos | D10: 0 | E10: 0 | F10: =+E10*D10 -> 0
B11: Alimentacion | D11: 0 | E11: 0 | F11: =+E11*D11 -> 0
B12: Subtotal | F12: =SUM(F7:F11) -> 230000
